sharedutils/__init__.py
sharedutils-0.0.7.dist-info/LICENSE
sharedutils-0.0.7.dist-info/METADATA
sharedutils-0.0.7.dist-info/WHEEL
sharedutils-0.0.7.dist-info/top_level.txt
sharedutils-0.0.7.dist-info/RECORD
